pyheartlib/__init__.py
pyheartlib/archs/__init__.py
pyheartlib/beat_info.py
pyheartlib/config.yaml
pyheartlib/data.py
pyheartlib/data_arrhythmia.py
pyheartlib/data_beat.py
pyheartlib/data_rhythm.py
pyheartlib/data_rpeak.py
pyheartlib/extra/__init__.py
pyheartlib/extra/pqrst.py
pyheartlib/extra/report.py
pyheartlib/extra/utils.py
pyheartlib/features.py
pyheartlib/io.py
pyheartlib/processing.py
pyheartlib-1.22.0.dist-info/LICENSE
pyheartlib-1.22.0.dist-info/METADATA
pyheartlib-1.22.0.dist-info/WHEEL
pyheartlib-1.22.0.dist-info/RECORD
