Metadata-Version: 2.1
Name: pyheartlib
Version: 1.22.0
Summary: A Python package for processing electrocardiogram signals
Home-page: https://github.com/devnums/pyheartlib
License: AGPL-3.0-only
Keywords: electrocardiogram,ECG
Author: devnums
Author-email: devnums.code@gmail.com
Requires-Python: >=3.10,<3.12
Classifier: License :: OSI Approved :: GNU Affero General Public License v3
Classifier: Programming Language :: Python :: 3
Classifier: Programming Language :: Python :: 3.10
Classifier: Programming Language :: Python :: 3.11
Requires-Dist: matplotlib (>=3.5.2)
Requires-Dist: numpy (>=1.22.0)
Requires-Dist: pandas (>=1.4.0)
Requires-Dist: pyyaml (>=6.0)
Requires-Dist: scikit-learn (>=1.1.0)
Requires-Dist: scipy (>=1.8.0)
Requires-Dist: tensorflow (>=2.8.0)
Requires-Dist: tqdm (>=4.63.0)
Requires-Dist: wfdb (>=4.0.0)
Project-URL: Documentation, https://pyheartlib.readthedocs.io
Project-URL: Repository, https://github.com/devnums/pyheartlib
